elk_ipam_search/config.py
elk_ipam_search/main.py
elk_ipam_search/utils/bodies.py
elk_ipam_search/utils/connectors.py
elk_ipam_search/vpo.txt
elk_ipam_search-0.1.1.dist-info/WHEEL
elk_ipam_search-0.1.1.dist-info/METADATA
elk_ipam_search-0.1.1.dist-info/RECORD
