Metadata-Version: 2.1
Name: elk-ipam-search
Version: 0.1.1
Summary: 
Author: Ilya Zakharov
Requires-Python: >=3.8,<4.0
Classifier: Programming Language :: Python :: 3
Classifier: Programming Language :: Python :: 3.8
Classifier: Programming Language :: Python :: 3.9
Classifier: Programming Language :: Python :: 3.10
Requires-Dist: elasticsearch (>=7.16.1,<7.17.0)
Requires-Dist: mailru-im-bot (==0.0.21)
